{
  "required": true,
  "minVersion": "0.8",
  "mixinextras": {
    "minVersion": "0.5.0"
  },
  "package": "net.theobl.worldofcolor.mixin",
  "compatibilityLevel": "JAVA_8",
  "refmap": "worldofcolor.refmap.json",
  "mixins": [
    "CauldronInteractionsMixin",
    "CopperChestBlockMixin",
    "HangingEntityItemMixin",
    "LayeredCauldronBlockMixin",
    "MapColorMixin",
    "ColorLerperMixin",
    "ShulkerBoxBlockMixin"
  ],
  "client": [
    "BedRendererMixin",
    "BlockStateDefinitionsMixin",
    "ChestRendererMixin",
    "CopperGolemStatueBlockRendererMixin",
    "ItemFrameRendererMixin",
    "LoomScreenMixin",
    "ShulkerBoxRendererMixin",
    "SpecialModelWrapperMixin",
    "TerrainParticleMixin"
  ],
  "injectors": {
    "defaultRequire": 1
  }
}
